algae/__init__.py
algae/either.py
algae/option.py
algae/py.typed
algae/try_.py
algae-1.1.0.dist-info/LICENSE.txt
algae-1.1.0.dist-info/WHEEL
algae-1.1.0.dist-info/METADATA
algae-1.1.0.dist-info/RECORD
