Metadata-Version: 2.1
Name: algae
Version: 1.1.0
Summary: Algebraic Data Types for Python
Home-page: https://github.com/lucaruzzola/algae
Keywords: python,ADT,algebraic,types,functional,programming,data,structures
Author: Luca Ruzzola
Author-email: lucaruzzola@gmail.com
Requires-Python: >=3.8,<4.0
Classifier: Programming Language :: Python :: 3
Classifier: Programming Language :: Python :: 3.10
Classifier: Programming Language :: Python :: 3.8
Classifier: Programming Language :: Python :: 3.9
Project-URL: Repository, https://github.com/lucaruzzola/algae
